haji.py
haji-0.1.0.dist-info/METADATA
haji-0.1.0.dist-info/WHEEL
haji-0.1.0.dist-info/entry_points.txt
haji-0.1.0.dist-info/top_level.txt
haji-0.1.0.dist-info/RECORD
